Workbook

Sheet Libro diario
C1: LIBRO DIARIO
C3: Nº | D3: FECHA | E3: CUENTA | F3: GLOSA | G3: DEBE | H3: HABER
C4: 1 | D4: 45658 | E4: 6 | F4: Balance de apertura 2025: Efectivo = bs 2726 , Banco: BNB = 13896; BMSC = 184 , David = bs -5. Total = bs 16801 | G4: 16801
E5: 1 | H5: 16801
C6: 2 | D6: 45658 | E6: 12 | F6: Movimiento de la cuenta BNB: 9,37 acreditado y 1,22 IVA, Saldo 8,15 de interés ganado | G6: 8.15
E7: 1 | H7: 8.15 | L7: Nº | M7: Libros mayores
C8: 3 | D8: 45658 | E8: 1 | F8: Movimiento de la cuenta BMSC: 0,26 acreditado y 0,03 IVA, Saldo 0,23 de interés ganado. Pago de seguro 15 = -14,77 | G8: 14.77 | L8: 1 | M8: Caja General
E9: 12 | H9: 14.77 | L9: 2 | M9: Materiales
C10: 4 | D10: 45658 | E10: 4 | F10: 1 Bomber Varón L Azul M. | G10: 100 | L10: 3 | M10: Ventas por mayor
E11: 1 | H11: 100 | L11: 4 | M11: Ventas por menor
C12: 5 | D12: 45658 | E12: 1 | F12: Encuentro con Paola. | G12: 44.2 | L12: 5 | M12: Pasajes
E13: 7 | H13: 44.2 | L13: 6 | M13: Patrimonio
C14: 6 | D14: 45658 | E14: 1 | F14: Tienda. | G14: 19 | L14: 7 | M14: Paseo
E15: 12 | H15: 19 | L15: 8 | M15: Ropa
C16: 7 | D16: 45659 | E16: 4 | F16: 1 Bomber Varón L Verde M. | G16: 100 | L16: 9 | M16: Pasaje material
E17: 1 | G17: 2 | L17: 10 | M17: Universidad
E18: 1 | H18: 100 | L18: 11 | M18: Gatitos
E19: 5 | H19: 2 | L19: 12 | M19: Gastos extras
C20: 8 | D20: 45659 | E20: 4 | F20: 1 Bomber Entero Nuevo XL Negro. | G20: 130 | L20: 13 | M20: Materiales Univ.
E21: 1 | H21: 130 | L21: 14 | M21: Anuncio Facebook
C22: 9 | D22: 45659 | E22: 4 | F22: 2 Bomber Varón M Negro y Verde M. 1,5 pasaje. | G22: 200 | L22: 15 | M22: Familia
E23: 1 | G23: 1.5
E24: 1 | H24: 200
E25: 5 | H25: 1.5
C26: 10 | D26: 45659 | E26: 15 | F26: Ingreso extra. | G26: 6
E27: 1 | H27: 6
C28: 11 | D28: 45659 | E28: 1 | F28: Salida con Paola. | G28: 143
E29: 7 | H29: 143
C30: 12 | D30: 45659 | E30: 4 | F30: 2 Bomber Varón XL Negro y Azul M. | G30: 200
E31: 1 | H31: 200
C32: 13 | D32: 45659 | E32: 4 | F32: 1 Bomber Varón L Negro | G32: 100
E33: 1 | H33: 100
C34: 14 | D34: 45659 | E34: 4 | F34: Cinturròn. | G34: 55
E35: 1 | H35: 55
C36: 15 | D36: 45659 | E36: 4 | F36: 3 Bomber Varón XL Negro, guindo y Verde M. | G36: 280
E37: 1 | H37: 280
C38: 16 | D38: 45659 | E38: 4 | F38: Croquetas 1 kg 22; atùn en lata 3unid: 27; 15 ispi deshiratado | G38: 64
E39: 1 | H39: 64
C40: 17 | D40: 45659 | E40: 4 | F40: 1 Bomber Varón L Negro | G40: 80
E41: 1 | H41: 80
C42: 18 | D42: 45660 | E42: 4 | F42: 1 Bomber Varón L Negro. 2 pasaje. | G42: 100
E43: 1 | G43: 2
E44: 1 | H44: 100
E45: 5 | H45: 2
C46: 19 | D46: 45660 | E46: 4 | F46: 1 Bomber Varón XL Azul M. 2 pasaje. | G46: 105
E47: 1 | G47: 2
E48: 1 | H48: 105
E49: 5 | H49: 2
C50: 20 | D50: 45660 | E50: 1 | F50: Agua gimnasio y masitas. | G50: 26
E51: 12 | H51: 26
C52: 21 | D52: 45660 | E52: 4 | F52: 1 Bomber Varón XL Negro | G52: 110
E53: 1 | H53: 110
C54: 22 | D54: 45660 | E54: 4 | F54: 1 Bomber Varón L Azul M. | G54: 100
E55: 1 | H55: 100
C56: 23 | D56: 45660 | E56: 4 | F56: 2 Bomber Varón L Negro | G56: 180
E57: 1 | H57: 180
C58: 24 | D58: 45660 | E58: 4 | F58: 1 Bomber Varón M Verde M. 7,2 pasaje. 10 delivery | G58: 100
E59: 1 | G59: 7.2
E60: 5 | G60: 10
E61: 1 | H61: 100
E62: 5 | H62: 7.2
E63: 1 | H63: 10
C64: 25 | D64: 45661 | E64: 1 | F64: Material comprado | G64: 307.63
E65: 2 | H65: 307.63
C66: 26 | D66: 45661 | E66: 1 | F66: Gastos extra | G66: 28
E67: 12 | H67: 28
C68: 27 | D68: 45661 | E68: 4 | F68: 1 Bomber Varón L Negro | G68: 100
E69: 1 | H69: 100
C70: 28 | D70: 45661 | E70: 4 | F70: 1 Bomber Varón XL Azul M. | G70: 110
E71: 1 | H71: 110
C72: 29 | D72: 45661 | E72: 4 | F72: 1 Bomber Varón M Guindo | G72: 100
E73: 1 | H73: 100
C74: 30 | D74: 45661 | E74: 4 | F74: 1 Bomber Varón XL Azul M. | G74: 100
E75: 1 | H75: 100
C76: 31 | D76: 45661 | E76: 1 | F76: Pasaje para cambio de talla. | G76: 4
E77: 5 | H77: 4
C78: 32 | D78: 45662 | E78: 4 | F78: 2 Bomber Varón XL Negro y Verde M. 6 pasaje. 5 delivery | G78: 200
E79: 1 | G79: 6
E80: 5 | G80: 5
E81: 1 | H81: 200
E82: 5 | H82: 6
E83: 1 | H83: 5
C84: 33 | D84: 45662 | E84: 4 | F84: 1 Bomber Varón L Verde M. | G84: 100
E85: 1 | H85: 100
C86: 34 | D86: 45662 | E86: 1 | F86: Encuentro con Paola. | G86: 42.3
E87: 7 | H87: 42.3
C88: 35 | D88: 45662 | E88: 1 | F88: Recarga Tarjeta Teleférico. | G88: 20
E89: 5 | H89: 20
C90: 36 | D90: 45663 | E90: 4 | F90: 1 Bomber Varón L Negro | G90: 100
E91: 1 | H91: 100
C92: 37 | D92: 45663 | E92: 4 | F92: 1 Bomber Varón L Negro. 2,5 pasaje. | G92: 100
E93: 1 | G93: 2.5
E94: 1 | H94: 100
E95: 5 | H95: 2.5
C96: 38 | D96: 45663 | E96: 4 | F96: 1 Bomber Varón M Azul M. | G96: 100
E97: 1 | H97: 100
C98: 39 | D98: 45663 | E98: 1 | F98: Encuentro con Paola. | G98: 26
E99: 7 | H99: 26
C100: 40 | D100: 45663 | E100: 1 | F100: Veterinario. | G100: 100
E101: 11 | H101: 100
...

Sheet Libros mayores
A1: N° de transacción | B1: 1 Caja General | E1: N° de transacción | F1: 2 Materiales | I1: N° de transacción | J1: 3 Ventas por mayor | M1: N° de transacción | N1: 4 Ventas por menor | Q1: N° de transacción | R1: 5 Pasajes | U1: N° de transacción | V1: 12 Gastos extra | Y1: N° de transacción | Z1: 7 Paseo | AC1: N° de transacción | AD1: 11 Gatitos | AG1: N° de transacción | AH1: 9 Pasaje material | AK1: N° de transacción | AL1: 8 Ropa | AO1: N° de transacción | AP1: 13 Materiales Univ. | AS1: N° de transacción | AT1: 14 Anuncio Facebook | AW1: N° de transacción | AX1: 15 Familia | BA1: N° de transacción | BB1: 10 Universidad | BE1: N° de transacción | BF1: 6 Patrimonio
B2: Debe | C2: Haber | F2: Debe | G2: Haber | J2: Debe | K2: Haber | N2: Debe | O2: Haber | R2: Debe | S2: Haber | V2: Debe | W2: Haber | Z2: Debe | AA2: Haber | AD2: Debe | AE2: Haber | AH2: Debe | AI2: Haber | AL2: Debe | AM2: Haber | AP2: Debe | AQ2: Haber | AT2: Debe | AU2: Haber | AX2: Debe | AY2: Haber | BB2: Debe | BC2: Haber | BF2: Debe | BG2: Haber
A3: ENERO
A5: 1 | C5: 16801 | BE5: 1 | BF5: 16801
A6: 2 | C6: 8.15 | U6: 2 | V6: 8.15
A7: 3 | B7: 14.77 | U7: 3 | W7: 14.77
A8: 4 | C8: 100 | M8: 4 | N8: 100
A9: 5 | B9: 44.2 | Y9: 5 | AA9: 44.2
A10: 6 | B10: 19 | U10: 6 | W10: 19
A11: 7 | B11: 2 | C11: 100 | M11: 7 | N11: 100 | Q11: 7 | S11: 2
A12: 8 | C12: 130 | M12: 8 | N12: 130
A13: 9 | B13: 1.5 | C13: 200 | M13: 9 | N13: 200 | Q13: 9 | S13: 1.5
A14: 10 | C14: 6 | AW14: 10 | AX14: 6
A15: 11 | B15: 143 | Y15: 11 | AA15: 143
A16: 12 | C16: 200 | M16: 12 | N16: 200
A17: 13 | C17: 100 | M17: 13 | N17: 100
A18: 14 | B18: 55 | AK18: 14 | AM18: 55
A19: 15 | C19: 280 | M19: 15 | N19: 280
A20: 16 | B20: 64 | AC20: 16 | AE20: 64
A21: 17 | C21: 80 | M21: 17 | N21: 80
A22: 18 | B22: 2 | C22: 100 | M22: 18 | N22: 100 | Q22: 18 | S22: 2
A23: 19 | B23: 2 | C23: 105 | M23: 19 | N23: 105 | Q23: 19 | S23: 2
A24: 20 | B24: 26 | U24: 20 | W24: 26
A25: 21 | C25: 110 | M25: 21 | N25: 110
A26: 22 | C26: 100 | M26: 22 | N26: 100
A27: 23 | C27: 180 | M27: 23 | N27: 180
A28: 24 | C28: 100 | M28: 24 | N28: 100
A29: 24 | B29: 7.2 | C29: 10 | Q29: 24 | R29: 10 | S29: 7.2
A30: 25 | B30: 307.63 | E30: 25 | G30: 307.63
A31: 26 | B31: 28 | U31: 26 | W31: 28
A32: 27 | C32: 100 | M32: 27 | N32: 100
A33: 28 | C33: 110 | M33: 28 | N33: 110
A34: 29 | C34: 100 | M34: 29 | N34: 100
A35: 30 | C35: 100 | M35: 30 | N35: 100
A36: 31 | B36: 4 | Q36: 31 | S36: 4
A37: 32 | C37: 200 | M37: 32 | N37: 200
A38: 32 | B38: 6 | C38: 5 | Q38: 32 | R38: 5 | S38: 6
A39: 33 | C39: 100 | M39: 33 | N39: 100
A40: 34 | B40: 42.3 | Y40: 34 | AA40: 42.3
A41: 35 | B41: 20 | Q41: 35 | S41: 20
A42: 36 | C42: 100 | M42: 36 | N42: 100
A43: 37 | B43: 2.5 | C43: 100 | M43: 37 | N43: 100 | Q43: 37 | S43: 2.5
A44: 38 | C44: 100 | M44: 38 | N44: 100
A45: 39 | B45: 26 | Y45: 39 | AA45: 26
A46: 40 | B46: 100 | AC46: 40 | AE46: 100
A47: 41 | C47: 200 | M47: 41 | N47: 200
A48: 42 | B48: 4 | C48: 100 | M48: 42 | N48: 100 | Q48: 42 | S48: 4
A49: 43 | C49: 200 | M49: 43 | N49: 200
A50: 44 | B50: 2 | Q50: 44 | S50: 2
A51: 45 | B51: 25 | U51: 45 | W51: 25
A52: 46 | B52: 15 | Q52: 46 | S52: 15
A53: 47 | B53: 94 | AC53: 47 | AE53: 94
A54: 48 | C54: 100 | M54: 48 | N54: 100
A55: 49 | C55: 100 | M55: 49 | N55: 100
A56: 50 | C56: 6 | Q56: 50 | R56: 6
A57: 51 | B57: 63 | Y57: 51 | AA57: 63
A58: 52 | B58: 2 | C58: 110 | M58: 52 | N58: 110 | Q58: 52 | S58: 2
A59: 53 | B59: 90 | E59: 53 | G59: 90
A60: 54 | B60: 2 | C60: 1118 | I60: 54 | J60: 1118 | Q60: 54 | S60: 2
A61: 55 | C61: 100 | M61: 55 | N61: 100
A62: 56 | C62: 200 | M62: 56 | N62: 200
A63: 57 | B63: 45.5 | Y63: 54 | AA63: 45.5
A64: 58 | C64: 80 | M64: 58 | N64: 80
A65: 59 | C65: 80 | M65: 59 | N65: 80
A66: 60 | C66: 80 | M66: 60 | N66: 80
A67: 61 | C67: 110 | M67: 61 | N67: 110
A68: 62 | C68: 202 | M68: 62 | N68: 202
A69: 63 | C69: 200 | M69: 63 | N69: 200
A70: 64 | B70: 15 | U70: 64 | W70: 15
A71: 65 | B71: 10 | U71: 65 | W71: 10
A72: 66 | B72: 213.1 | Y72: 66 | AA72: 213.1
A73: 67 | B73: 75 | AK73: 67 | AM73: 75
A74: 68 | B74: 30 | AC74: 68 | AE74: 30
A75: 69 | B75: 13389 | E75: 69 | G75: 13389
A76: 69 | B76: 44 | AG76: 69 | AI76: 44
A77: 70 | C77: 100 | M77: 70 | N77: 100
A78: 71 | C78: 100 | M78: 71 | N78: 100
A79: 72 | C79: 180 | M79: 72 | N79: 180
A80: 73 | B80: 5 | Q80: 73 | S80: 5
A81: 74 | C81: 100 | M81: 74 | N81: 100
A82: 75 | C82: 100 | M82: 75 | N82: 100
A83: 76 | B83: 50 | Q83: 76 | S83: 50
A84: 77 | B84: 3.5 | Q84: 77 | S84: 3.5
A85: 78 | C85: 100 | M85: 78 | N85: 100
A86: 79 | C86: 205 | M86: 79 | N86: 205
A87: 80 | C87: 100 | M87: 80 | N87: 100
A88: 81 | B88: 5.5 | Q88: 81 | S88: 5.5
A89: 82 | B89: 55.4 | Y89: 82 | AA89: 55.4
A90: 83 | B90: 142 | E90: 83 | G90: 142
A91: 84 | B91: 99 | AC91: 84 | AE91: 99
A92: 85 | C92: 100 | M92: 85 | N92: 100
A93: 86 | C93: 180 | M93: 86 | N93: 180
A94: 87 | C94: 220 | M94: 87 | N94: 220
A95: 88 | C95: 110 | M95: 88 | N95: 110
A96: 89 | B96: 4 | Q96: 89 | S96: 4
A97: 90 | B97: 55 | AC97: 90 | AE97: 55
A98: 91 | B98: 26 | U98: 91 | W98: 26
A99: 92 | C99: 180 | M99: 92 | N99: 180
A100: 93 | C100: 200 | M100: 93 | N100: 200
A101: 94 | B101: 2 | Q101: 94 | S101: 2
...

Sheet Material comprado
C1: MATERIAL COMPRADO | W1: Código | X1: Descripciòn de prenda | Y1: Género | Z1: Materiales
W2: 1 | X2: Bombers | Y2: Varón | Z2: Jaypura, polar andino, tafeta, pretina común negra, cierre de aluminio, cierre 12cm de aluminio para manga.
W3: 2 | X3: Bombers | Y3: Dama | Z3: Jaypura, polar andino, tafeta, pretina común negra, cierre de aluminio, cierre 12cm de aluminio para manga.
W4: 3 | X4: Bombers kaki | Y4: Varón | Z4: Kaki 1ra, polar andino, tafeta, pretina de lana negra, cierre de aluminio, cierre 12cm de aluminio para manga.
W5: 4 | X5: Bombers Cuerina | Y5: Varón | Z5: Cuerina, tafeta, pretina común negra, cierre aluminio opaco, cierre aluminio 12 cm para manga.
W6: 5 | X6: Bombers enteras | Y6: Varón | Z6: Jaypura, Tafeta, Cierre coreano, pretina comùn del color de la prenda, cierre de la manga del color de la prenda, llave cromada invertida.
W7: 6 | X7: Bombers enteras | Y7: Dama | Z7: Jaypura, Tafeta, Cierre coreano, pretina comùn del color de la prenda, cierre de la manga del color de la prenda, llave cromada invertida.
W8: 7 | X8: Chamarras acolchadas | Y8: Varón | Z8: Mojado coreano, polar andino, cierre nylon, cierres nylon para 3 bolsillos, llaves min, liga de 3cm.
W9: 8 | X9: Chamarras acolchadas | Y9: Dama | Z9: Mojado coreano, polar andino, cierre nylon, cierres nylon para 3 bolsillos, llaves min, liga de 3cm.
W10: 9 | X10: Chamarra Acolchada Crop | Y10: Dama | Z10: Mojado coreano, polar andino, cierre nylon, cierres nylon para 3 bolsillos, llaves min, liga de 3cm.
W11: 10 | X11: Chalecos acolchados | Y11: Varón | Z11: Mojado coreano, polar andino, cierre nylon, cierres nylon para 3 bolsillos, llaves min, cinta de ribete elástica de 2cm del color de la prenda.
W12: 11 | X12: Joggers | Y12: Unisex | Z12: Terry, wato del color de la prenda, liga de 4cm.
W13: 12 | X13: Canguros | Y13: Varón | Z13: Terry.
... W17: 16 | X17: Chamarras acolchadas | Y17: Dama | Z17: Taslan arrugado, fibra, polar plusher, terry, pretina común del color de la prenda, cierrre coreano normal del color de la prenda, llave especial
W18: 17 | X18: =X17 -> Chamarras acolchadas | Y18: =Y17 -> Dama | Z18: =Z17 -> Taslan arrugado, fibra, polar plusher, terry, pretina común del color de la prenda, cierrre coreano normal del color de la prenda, llave especial
W19: 18 | X19: Bomber polinylon | Y19: Varón | Z19: Polinylon, polar andino, tafeta, tira de 150 cm de pretina poliéster, cierre nylon oro, llaves especiales
W20: 19 | X20: Bomber polinylon | Y20: Dama | Z20: Polinylon, polar andino, tafeta, tira de 150 cm de pretina poliéster, cierre nylon oro, llaves especiales
W21: 20 | X21: Chaqueta Camisa | Y21: Varón | Z21: Kaki 1ra, Tafeta, Cierre Nylon ORO, Tira pretina grueso, pellón.
W22: 21 | X22: Nuevo Bomber Entero | Y22: Varón | Z22: Jaypura, polar andino, tafeta, pretina poliéster primera, cierre nylon ORO, cierre xm nylon ORO con llave ORO.
W23: 22 | X23: Canguros | Y23: Varón | Z23: Terry y cierre nylon normal centreal.
C30: Nº | D30: Fecha | F30: Tipo de prenda | N30: Código | O30: Pedido | Q30: Cliente
O31: si | P31: no
C32: Detalle del pedido | L32: Material comprado
C33: Talla | L33: Material | N33: Color | O33: m | P33: P x m | Q33: Total | R33: TOTAL
C43: Nº | D43: Fecha | F43: Tipo de prenda | O43: Código | P43: Pedido | R43: Cliente
P44: si | Q44: no
F45: Nº pedido a completar
D47: Material | H47: Color | M47: m | O47: P x m | P47: Total | Q47: TOTAL
P48: =M48*O48 -> 0 | Q48: =SUM(P48:P49) -> 0
P49: =M49*O49 -> 0
C53: Nº | D53: Fecha | F53: Tipo de prenda | N53: Código | O53: Pedido | Q53: Cliente
C54: 25 | D54: 45661 | F54: Bomber Varón | N54: 1 | O54: si | P54: no | Q54: N/A
C55: Detalle del pedido | L55: Material comprado
C56: Talla | F56: L | G56: XL | L56: Material | N56: Color | O56: m | P56: P x m | Q56: Total | R56: TOTAL
C57: Negro | G57: 8 | L57: Polar andino | N57: Negro | O57: 22 | P57: 7 | Q57: =P57*O57 -> 154 | R57: =SUM(Q57:Q60) -> 307.63
C58: Verde M | F58: 4 | L58: Cierres aluminio | N58: Plateado | O58: 12 | P58: =30/12 -> 2.5 | Q58: =P58*O58 -> 30
L59: Pretina común | N59: Negro | O59: 2 | P59: 27 | Q59: =P59*O59 -> 54
L60: Photoshop | O60: 1 | P60: 69.63 | Q60: =P60*O60 -> 69.63
C64: Nº | D64: Fecha | F64: Tipo de prenda | N64: Código | O64: Pedido | Q64: Cliente
C65: 53 | D65: 45665 | F65: Nuevo Bomber Entero | N65: 21 | O65: si | P65: no | Q65: N/A
C66: Detalle del pedido | L66: Material comprado
C67: Talla | F67: L | G67: XL | L67: Material | N67: Color | O67: m | P67: P x m | Q67: Total | R67: TOTAL
C68: Negro | F68: 3 | G68: 1 | L68: Polar andino | N68: Negro | O68: 20 | P68: 2.5 | Q68: =P68*O68 -> 50 | R68: =SUM(Q68:Q69) -> 90
L69: Pretina en tiras | N69: Negro | O69: 4 | P69: 10 | Q69: =P69*O69 -> 40
C73: Nº | D73: Fecha | F73: Tipo de prenda | N73: Código | O73: Pedido | Q73: Cliente
C74: 69 | D74: 45667 | F74: Bomber Varón | N74: 1 | O74: si | P74: no | Q74: N/A
C75: Detalle del pedido | L75: Material comprado
C76: Talla | E76: S | F76: M | G76: L | H76: XL | I76: XXL | L76: Material | N76: Color | O76: m | P76: P x m | Q76: Total | R76: TOTAL
C77: Negro | F77: 32 | G77: =F77+H77 -> 62 | H77: 30 | L77: Polar andino | N77: Negro | O77: 70 | P77: =1290/O77 -> 18.428571 | Q77: =P77*O77 -> 1290 | R77: =SUM(Q77:Q82) -> 13389
C78: Azul M | F78: 12 | G78: =F78+H78 -> 24 | H78: 12 | L78: Pretina común | N78: Negro | O78: 16.4 | P78: =1110/O78 -> 67.682927 | Q78: =P78*O78 -> 1110
C79: Verde M | F79: 12 | G79: =F79+H79 -> 24 | H79: 12 | L79: Jaypura | N79: Negro | O79: 200 | P79: 22.2 | Q79: =P79*O79 -> 4440
C80: Guindo | F80: 12 | G80: =F80+H80 -> 24 | H80: 12 | N80: Azul M | O80: 100 | P80: 22.2 | Q80: =P80*O80 -> 2220
N81: Verde M | O81: 95 | P81: 22.2 | Q81: =P81*O81 -> 2109
N82: Guindo | O82: 100 | P82: 22.2 | Q82: =P82*O82 -> 2220
J83: =SUM(E77:I80) -> 268
C86: Nº | D86: Fecha | F86: Tipo de prenda | O86: Código | P86: Pedido | R86: Cliente
C87: 83 | D87: 45670 | F87: Bomber Varón | O87: 1 | P87: si | Q87: no | R87: N/A
F88: Nº pedido a completar
F89: 69
D90: Material | H90: Color | M90: m | O90: P x m | P90: Total | Q90: TOTAL
D91: Cierre aluminio | H91: 12 cm | M91: 240 | O91: =71/120 -> 0.59166667 | P91: =M91*O91 -> 142 | Q91: =SUM(P91:P91) -> 142
C95: Nº | D95: Fecha | F95: Tipo de prenda | N95: Código | O95: Pedido | Q95: Cliente
C96: 97 | D96: 45672 | F96: Bomber Varón | N96: 1 | O96: si | P96: no | Q96: FECOMAN
C97: Detalle del pedido | L97: Material comprado
C98: Talla | E98: S | F98: M | G98: L | H98: XL | I98: XXL | L98: Material | N98: Color | O98: m | P98: P x m | Q98: Total | R98: TOTAL
C99: Azul M | F99: 1 | H99: 3 | I99: 2 | L99: Polar andino | N99: Negro | O99: 12 | P99: 20 | Q99: =P99*O99 -> 240 | R99: =SUM(Q99:Q103) -> 909.5
C100: Petróleo | I100: 2 | L100: Pretina en tiras | N100: Azul M. | O100: 4 | P100: 10 | Q100: =P100*O100 -> 40
L101: cierre nylon ORO | N101: Azul M. | O101: 6 | P101: =47/12 -> 3.9166667 | Q101: =P101*O101 -> 23.5
L102: Tafeta | N102: Negro | O102: 10 | P102: 5 | Q102: =P102*O102 -> 50
L103: Cierre aluminio | N103: Plateado | O103: 2 | P103: 278 | Q103: =P103*O103 -> 556
J104: =SUM(E99:I102) -> 8
C107: Nº | D107: Fecha | F107: Tipo de prenda | N107: Código | O107: Pedido | Q107: Cliente
C108: 99 | D108: 45673 | F108: Bomber Varón | N108: 1 | O108: si | P108: no | Q108: DAVID
C109: Detalle del pedido | L109: Material comprado
C110: Talla | E110: S | F110: M | G110: L | H110: XL | I110: 4XL | L110: Material | N110: Color | O110: m | P110: P x m | Q110: Total | R110: TOTAL
C111: Verde Hoja seca | G111: 8 | H111: 5 | I111: 1 | L111: Jaypura | N111: Verde Hoja seca | O111: 15.5 | P111: =360/O111 -> 23.225806 | Q111: =P111*O111 -> 360 | R111: =SUM(Q111:Q112) -> 370
L112: Pretina en tiras | N112: Azul M. | O112: 1 | P112: 10 | Q112: =P112*O112 -> 10
J113: =SUM(E111:I111) -> 14
C116: Nº | D116: Fecha | F116: Tipo de prenda | N116: Código | O116: Pedido | Q116: Cliente
C117: 110 | D117: 45674 | F117: Bomber Varón | N117: 1 | O117: si | P117: no | Q117: MALLEA
C118: Detalle del pedido | L118: Material comprado
C119: Talla | E119: S | F119: M | G119: L | H119: XL | I119: XXL | L119: Material | N119: Color | O119: m | P119: P x m | Q119: Total | R119: TOTAL
C120: Azul M | L120: Polinylon | N120: Azul M. | O120: 24.5 | P120: =440/O120 -> 17.959184 | Q120: =P120*O120 -> 440 | R120: =SUM(Q120:Q123) -> 905
L121: Llaves ORO | N121: Plateado | O121: 100 | P121: 1.16 | Q121: =P121*O121 -> 116
L122: Cierres ORO | N122: Azul M. | O122: 24 | P122: =47/12 -> 3.9166667 | Q122: =P122*O122 -> 94
L123: Pretina en tiras | N123: Azul M. | O123: 27 | P123: =255/O123 -> 9.4444444 | Q123: =P123*O123 -> 255
J124: =SUM(E120:I122) -> 0
C127: Nº | D127: Fecha | F127: Tipo de prenda | O127: Código | P127: Pedido | R127: Cliente
C128: 135 | D128: 45680 | F128: Bomber Varón | O128: 1 | P128: si | Q128: no | R128: DAVID
F129: Nº pedido a completar
F130: 99
D131: Material | H131: Color | M131: m | O131: P x m | P131: Total | Q131: TOTAL
D132: Cierre ORO | H132: Negro | M132: 12 | O132: =47.5/12 -> 3.9583333 | P132: =M132*O132 -> 47.5 | Q132: =SUM(P132:P132) -> 47.5
C136: Nº | D136: Fecha | F136: Tipo de prenda | O136: Código | P136: Pedido | R136: Cliente
C137: 148 | D137: 45683 | P137: si | Q137: no | R137: N/A
F138: Nº pedido a completar
D140: Material | H140: Color | M140: m | O140: P x m | P140: Total | Q140: TOTAL
D141: Repuestos | H141: Recta | M141: 1 | O141: 90 | P141: =M141*O141 -> 90 | Q141: =SUM(P141:P141) -> 90
C145: Nº | D145: Fecha | F145: Tipo de prenda | N145: Código | O145: Pedido | Q145: Cliente
C146: 150 | D146: 45684 | F146: Bomber Varón | N146: 1 | O146: si | P146: no | Q146: FECOMAN
...

Sheet Prendas realizadas
C1: PRENDAS REALIZADAS | O1: Código | P1: Descripciòn de prenda | Q1: Género | R1: Materiales
O2: 1 | P2: Bombers | Q2: Varón | R2: Jaypura, polar andino, tafeta, pretina común negra, cierre de aluminio, cierre 12cm de aluminio para manga.
C3: Nº | D3: Código | E3: Nombre de prenda | F3: Cantidad | G3: Cliente | H3: Fechas | O3: 2 | P3: Bombers | Q3: Dama | R3: Jaypura, polar andino, tafeta, pretina común negra, cierre de aluminio, cierre 12cm de aluminio para manga.
H4: Cot. | I4: comp. | J4: Cort. | K4: Term. | O4: 3 | P4: Bombers kaki | Q4: Varón | R4: Kaki 1ra, polar andino, tafeta, pretina de lana negra, cierre de aluminio, cierre 12cm de aluminio para manga.
C5: 25 | D5: 1 | E5: Bomber Varón | F5: 8 | G5: N/A | H5: 45661 | I5: 45661 | J5: 45661 | K5: 45663 | O5: 4 | P5: Bombers Cuerina | Q5: Varón | R5: Cuerina, tafeta, pretina común negra, cierre aluminio opaco, cierre aluminio 12 cm para manga.
C6: 53 | D6: 21 | E6: Nuevo Bomber Entero | F6: 4 | G6: 67918000 | H6: 45665 | I6: 45665 | J6: 45665 | K6: 45665 | O6: 5 | P6: Bombers enteras | Q6: Varón | R6: Jaypura, Tafeta, Cierre coreano, pretina comùn del color de la prenda, cierre de la manga del color de la prenda, llave cromada invertida.
C7: 69 | D7: 1 | E7: Bomber Varón | F7: =268-F8-F10-F14-F16-F19-F20-F21-F22-F24-F26-F29-F36-F41-F47 -> 38 | G7: N/A | H7: 45667 | I7: 45667 | J7: 45669 | O7: 6 | P7: Bombers enteras | Q7: Dama | R7: Jaypura, Tafeta, Cierre coreano, pretina comùn del color de la prenda, cierre de la manga del color de la prenda, llave cromada invertida.
C8: 69 | D8: 1 | E8: Bomber Varón | F8: 32 | G8: N/A | H8: 45667 | I8: 45667 | J8: 45669 | K8: 45673 | O8: 7 | P8: Chamarras acolchadas | Q8: Varón | R8: Mojado coreano, polar andino, cierre nylon, cierres nylon para 3 bolsillos, llaves min, liga de 3cm.
C9: 98 | D9: 1 | E9: Bomber Varón | F9: 1 | G9: Leandro | H9: 45673 | I9: 45673 | J9: 45673 | K9: 45673 | O9: 8 | P9: Chamarras acolchadas | Q9: Dama | R9: Mojado coreano, polar andino, cierre nylon, cierres nylon para 3 bolsillos, llaves min, liga de 3cm.
C10: 69 | D10: 21 | E10: Nuevo Bomber Entero | F10: 4 | G10: FECOMAN | H10: 45667 | I10: 45667 | J10: 45669 | K10: 45674 | O10: 9 | P10: Chalecos acolchados | Q10: Varón | R10: Mojado coreano, polar andino, cierre nylon, cierres nylon para 3 bolsillos, llaves min, cinta de ribete elástica de 2cm del color de la prenda.
C11: 106 | D11: 21 | E11: Nuevo Bomber Entero | F11: 4 | G11: FECOMAN | H11: 45667 | I11: 45667 | J11: 45669 | K11: 45674 | O11: 10 | P11: Joggers | Q11: Unisex | R11: Terry, wato del color de la prenda, liga de 4cm.
C12: 110 | D12: 18 | E12: Bomber Polinylon | F12: 19 | G12: Mallea | H12: 45674 | I12: 45674 | J12: 45676 | K12: 45678 | O12: 11 | P12: Canguros | Q12: Varón | R12: Terry.
C13: 99 | D13: 14 | E13: Bomber Varón | F13: 14 | G13: DAVID | H13: 45673 | I13: 45680 | J13: 45680 | K13: 45682 | O13: 12 | P13: Canguros | Q13: Dama | R13: Terry.
C14: 69 | D14: 1 | E14: Bomber Varón | F14: 44 | G14: N/A | H14: 45667 | I14: 45667 | J14: 45669 | K14: 45683 | O14: 13 | P14: Polerones | Q14: Varón | R14: Terry, pretina de polera.
C15: 150 | D15: 21 | E15: Nuevo Bomber Entero | F15: 41 | G15: FECOMAN | H15: 45684 | I15: 45684 | J15: 45685 | K15: 45687 | O15: 14 | P15: Chamarras acolchadas | Q15: Varón | R15: Taslan arrugado, fibra, polar plusher, terry, pretina común del color de la prenda, cierrre coreano normal del color de la prenda, llave especial
C16: 69 | D16: 1 | E16: Bomber Varón | F16: 30 | G16: N/A | H16: 45667 | I16: 45667 | J16: 45669 | K16: 45690 | O16: 15 | P16: Chamarras acolchadas | Q16: Dama | R16: Taslan arrugado, fibra, polar plusher, terry, pretina común del color de la prenda, cierrre coreano normal del color de la prenda, llave especial
C17: 167 | D17: 7 | E17: Chamarras acolchadas Varón | F17: 8 | G17: Fabrizio | H17: 45687 | I17: 45687 | J17: 45690 | K17: 45692 | O17: 15 | P17: Chamarras acolchadas | Q17: Dama | R17: Taslan arrugado, fibra, polar plusher, terry, pretina común del color de la prenda, cierrre coreano normal del color de la prenda, llave especial
C18: 167 | D18: 9 | E18: Chalecos acolchados | F18: 1 | G18: Fabrizio | H18: 45687 | I18: 45687 | J18: 45690 | K18: 45692
C19: 69 | D19: 1 | E19: Bomber Varón | F19: 26 | G19: N/A | H19: 45667 | I19: 45667 | J19: 45669 | K19: 45695
C20: 69 | D20: 1 | E20: Bomber Varón | F20: 12 | G20: N/A | H20: 45667 | I20: 45667 | J20: 45669 | K20: 45698
C21: 69 | D21: 1 | E21: Bomber Varón | F21: 18 | G21: N/A | H21: 45667 | I21: 45667 | J21: 45669 | K21: 45701
C22: 69 | D22: 1 | E22: Bomber Varón | F22: 9 | G22: N/A | H22: 45667 | I22: 45667 | J22: 45669 | K22: 45704
D23: 1 | E23: Bomber Varón | F23: =4-F30-F37 -> 0 | G23: N/A | H23: 45667 | I23: 45667 | J23: 45669
C24: 69 | D24: 1 | E24: Bomber Varón | F24: =2+4+3+5 -> 14 | G24: Sucre | H24: 45667 | I24: 45667 | J24: 45669 | K24: 45707
C25: 278 | D25: 1 | E25: Bomber Varón | F25: 20 | G25: Sucre | H25: 45667 | I25: 45667 | J25: 45669 | K25: 45707
C26: 69 | D26: 1 | E26: Bomber Varón | F26: 24 | G26: N/A | H26: 45667 | I26: 45667 | J26: 45669 | K26: 45712
C27: 327 | E27: Chamarras Sooftshell | F27: 30 | G27: Jhonny | H27: 45712 | I27: 45713 | J27: 45713 | K27: 45718
C28: 369 | D28: 5 | E28: Bomber entero Varón | F28: 1 | G28: Fabrizio | H28: 45714 | I28: 45717 | J28: 45719 | K28: 45721
C29: 69 | D29: 5 | E29: Bomber entero Varón | F29: 12 | G29: Fabrizio | H29: 45714 | I29: 45717 | J29: 45719 | K29: 45721
D30: 5 | E30: Bomber entero Varón | F30: 3 | G30: Fabrizio | H30: 45714 | I30: 45717 | J30: 45719 | K30: 45721
D31: 18 | E31: Bomber entero Varón | F31: 11 | G31: Mallea | H31: 45714 | I31: 45717 | J31: 45722 | K31: 45722
D32: 21 | E32: Nuevo Bomber Entero | F32: 5 | G32: FECOMAN | H32: 45726 | I32: 45726 | J32: 45726 | K32: 45726
D33: 18 | E33: Bomber entero Varón | F33: 3 | G33: Mallea | H33: 45726 | I33: 45726 | J33: 45726 | K33: 45727
D34: 21 | E34: Nuevo Bomber Entero | F34: 18 | G34: FECOMAN | H34: 45725 | I34: 45727 | J34: 45727 | K34: 45729
D35: 1 | E35: Bomber Varón | F35: 7 | G35: Leandro | H35: 45728 | I35: 45667 | J35: 45730 | K35: 45733
C36: 69 | D36: 1 | E36: Bomber Varón | F36: 2 | G36: Leandro | H36: 45728 | I36: 45667 | J36: 45730 | K36: 45733
D37: 1 | E37: Bomber Varón | F37: 1 | G37: Leandro | H37: 45728 | I37: 45667 | J37: 45730 | K37: 45733
C38: 427 | D38: 1 | E38: Bomber Varón | F38: =288-F39-F42-F48-F50 -> 271 | G38: N/A | H38: 45730 | I38: 45730 | J38: 45739
C39: 427 | D39: 1 | E39: Bomber Varón | F39: 6 | G39: N/A | H39: 45730 | I39: 45730 | J39: 45739 | K39: 45741
D40: 1 | E40: Bomber Varón | F40: 2 | G40: Leandro | H40: 45728 | I40: 45667 | J40: 45746 | K40: 45748
C41: 69 | D41: 1 | E41: Bomber Varón | F41: 1 | G41: Leandro | H41: 45728 | I41: 45667 | J41: 45730 | K41: 45748
C42: 427 | D42: 1 | E42: Bomber Varón | F42: 3 | G42: Leandro | H42: 45730 | I42: 45730 | J42: 45739 | K42: 45748
D43: 1 | E43: Bomber Dama | F43: 1 | G43: Leandro | H43: 45728 | I43: 45667 | J43: 45746 | K43: 45748
D44: 1 | E44: Bomber Varón | F44: =3-F45 -> 2 | G44: N/A | H44: 45751 | I44: 45667 | J44: 45751 | K44: 45753
D45: 1 | E45: Bomber Varón | F45: 1 | G45: Leandro | H45: 45751 | I45: 45667 | J45: 45751 | K45: 45753
D46: 1 | E46: Bomber Varón | F46: 7 | G46: Leandro | H46: 45751 | I46: 45667 | J46: 45751 | K46: 45753
C47: 69 | D47: 1 | E47: Bomber Varón | F47: 2 | G47: Leandro | H47: 45667 | I47: 45667 | J47: 45669 | K47: 45753
C48: 427 | D48: 1 | E48: Bomber Varón | F48: 4 | G48: Leandro | H48: 45730 | I48: 45730 | J48: 45739 | K48: 45753
E49: Chamarra Limber | F49: 19 | G49: Infocal | H49: 45754 | I49: 45754 | J49: 45755 | K49: 45758
C50: 427 | D50: 1 | E50: Bomber Varón | F50: 4 | G50: Leandro | H50: 45730 | I50: 45730 | J50: 45739 | K50: 45756
D51: 1 | E51: Bomber Varón | F51: 3 | G51: FECOMAN | H51: 45758 | I51: 45667 | J51: 45758 | K51: 45761
C52: 69 | D52: 1 | E52: Bomber Varón | F52: 14 | G52: FECOMAN | H52: 45728 | I52: 45667 | J52: 45730 | K52: 45761
C53: 427 | D53: 1 | E53: Bomber Varón | F53: 23 | G53: FECOMAN | H53: 45730 | I53: 45730 | J53: 45739 | K53: 45761

Sheet Ventas por mayor
C1: VENTAS POR MAYOR | O1: Código | P1: Descripciòn de prenda | Q1: Género | R1: Materiales
O2: 1 | P2: Bombers | Q2: Varón | R2: Jaypura, polar andino, tafeta, pretina común negra, cierre de aluminio, cierre 12cm de aluminio para manga.
C3: Nº | D3: Fecha | E3: Código | F3: Nombre de prenda | G3: Cantidad | H3: Cliente | I3: Precio | O3: 2 | P3: Bombers | Q3: Dama | R3: Jaypura, polar andino, tafeta, pretina común negra, cierre de aluminio, cierre 12cm de aluminio para manga.
I4: Unitario | J4: Total | O4: 3 | P4: Bombers kaki | Q4: Varón | R4: Kaki 1ra, polar andino, tafeta, pretina de lana negra, cierre de aluminio, cierre 12cm de aluminio para manga.
C5: 54 | D5: 45665 | E5: 21 | F5: Nuevo Bomber Entero | G5: 13 | H5: 67918000 | I5: 86 | J5: =I5*G5 -> 1118 | O5: 4 | P5: Bombers Cuerina | Q5: Varón | R5: Cuerina, tafeta, pretina común negra, cierre aluminio opaco, cierre aluminio 12 cm para manga.
O6: 5 | P6: Bombers enteras | Q6: Varón | R6: Jaypura, Tafeta, Cierre coreano, pretina comùn del color de la prenda, cierre de la manga del color de la prenda, llave cromada invertida.
O7: 6 | P7: Bombers enteras | Q7: Dama | R7: Jaypura, Tafeta, Cierre coreano, pretina comùn del color de la prenda, cierre de la manga del color de la prenda, llave cromada invertida.
O8: 7 | P8: Chamarras acolchadas | Q8: Varón | R8: Mojado coreano, polar andino, cierre nylon, cierres nylon para 3 bolsillos, llaves min, liga de 3cm.
O9: 8 | P9: Chamarras acolchadas | Q9: Dama | R9: Mojado coreano, polar andino, cierre nylon, cierres nylon para 3 bolsillos, llaves min, liga de 3cm.
O10: 9 | P10: Chamarra Acolchada Crop | Q10: Dama | R10: Mojado coreano, polar andino, cierre nylon, cierres nylon para 3 bolsillos, llaves min, liga de 3cm.
O11: 10 | P11: Chalecos acolchados | Q11: Varón | R11: Mojado coreano, polar andino, cierre nylon, cierres nylon para 3 bolsillos, llaves min, cinta de ribete elástica de 2cm del color de la prenda.
O12: 11 | P12: Joggers | Q12: Unisex | R12: Terry, wato del color de la prenda, liga de 4cm.
O13: 12 | P13: Canguros | Q13: Varón | R13: Terry.
O14: 13 | P14: Canguros | Q14: Dama | R14: Terry.
O15: 14 | P15: Polerones | Q15: Varón | R15: Terry, pretina de polera.
O16: 15 | P16: Chamarras acolchadas | Q16: Varón | R16: Taslan arrugado, fibra, polar plusher, terry, pretina común del color de la prenda, cierrre coreano normal del color de la prenda, llave especial
O17: 16 | P17: Chamarras acolchadas | Q17: Dama | R17: Taslan arrugado, fibra, polar plusher, terry, pretina común del color de la prenda, cierrre coreano normal del color de la prenda, llave especial
O18: 17 | P18: =P17 -> Chamarras acolchadas | Q18: =Q17 -> Dama | R18: =R17 -> Taslan arrugado, fibra, polar plusher, terry, pretina común del color de la prenda, cierrre coreano normal del color de la prenda, llave especial
O19: 18 | P19: Bomber polinylon | Q19: Varón | R19: Polinylon, polar andino, tafeta, tira de 150 cm de pretina poliéster, cierre nylon oro, llaves especiales
O20: 19 | P20: Bomber polinylon | Q20: Dama | R20: Polinylon, polar andino, tafeta, tira de 150 cm de pretina poliéster, cierre nylon oro, llaves especiales
O21: 20 | P21: Chaqueta Camisa | Q21: Varón | R21: Kaki 1ra, Tafeta, Cierre Nylon ORO, Tira pretina grueso, pellón.
O22: 21 | P22: Bomber Entero Nuevo | Q22: Varón | R22: Jaypura, polar andino, tafeta, pretina poliéster primera, cierre nylon ORO, cierre xm nylon ORO con llave ORO.
O23: 22 | P23: Canguros | Q23: Varón | R23: Terry y cierre nylon normal centreal.

Sheet Ventas por menor
C1: VENTAS POR MENOR | R1: Código | S1: Descripciòn de prenda | T1: Género | U1: Materiales
R2: 1 | S2: Bombers | T2: Varón | U2: Jaypura, polar andino, tafeta, pretina común negra, cierre de aluminio, cierre 12cm de aluminio para manga.
C3: Nº | D3: Fecha | E3: Código | F3: Nombre de prenda | G3: Cantidad | H3: Color | I3: Talla | J3: Precio | K3: Lugar | L3: Vendedor | M3: TOTAL | R3: 2 | S3: Bombers | T3: Dama | U3: Jaypura, polar andino, tafeta, pretina común negra, cierre de aluminio, cierre 12cm de aluminio para manga.
C4: ENERO | R4: 3 | S4: Bombers kaki | T4: Varón | U4: Kaki 1ra, polar andino, tafeta, pretina de lana negra, cierre de aluminio, cierre 12cm de aluminio para manga.
C5: 4 | E5: 1 | F5: Bomber Varón | G5: 1 | H5: Azul M. | I5: L | J5: 100 | K5: San Francisco | L5: Rossell | M5: =G5*J5 -> 100 | R5: 4 | S5: Bombers Cuerina | T5: Varón | U5: Cuerina, tafeta, pretina común negra, cierre aluminio opaco, cierre aluminio 12 cm para manga.
C6: 7 | E6: 1 | F6: Bomber Varón | G6: 1 | H6: Verde M. | I6: L | J6: 100 | K6: Tlf. Cotahuma | L6: Rossell | M6: =J6*G6 -> 100 | R6: 5 | S6: Bombers enteras | T6: Varón | U6: Jaypura, Tafeta, Cierre coreano, pretina comùn del color de la prenda, cierre de la manga del color de la prenda, llave cromada invertida.
C7: 8 | E7: 1 | F7: Nuevo Bomber Entero | G7: 1 | H7: Negro | I7: XL | J7: 130 | K7: Sucre | L7: Rossell | M7: =J7*G7 -> 130 | R7: 6 | S7: Bombers enteras | T7: Dama | U7: Jaypura, Tafeta, Cierre coreano, pretina comùn del color de la prenda, cierre de la manga del color de la prenda, llave cromada invertida.
C8: 9 | E8: 1 | F8: Bomber Varón | G8: 1 | H8: Negro | I8: M | J8: 100 | K8: Cochabamba | L8: Rossell | M8: =J8*G8 -> 100 | R8: 7 | S8: Chamarras acolchadas | T8: Varón | U8: Mojado coreano, polar andino, cierre nylon, cierres nylon para 3 bolsillos, llaves min, liga de 3cm.
G9: 1 | H9: Verde M. | I9: M | J9: 100 | M9: =J9*G9 -> 100 | R9: 8 | S9: Chamarras acolchadas | T9: Dama | U9: Mojado coreano, polar andino, cierre nylon, cierres nylon para 3 bolsillos, llaves min, liga de 3cm.
C10: 12 | E10: 1 | F10: Bomber Varón | G10: 1 | H10: Negro | I10: XL | J10: 100 | K10: Potosí | L10: Rossell | M10: =J10*G10 -> 100 | R10: 9 | S10: Chamarra Acolchada Crop | T10: Dama | U10: Mojado coreano, polar andino, cierre nylon, cierres nylon para 3 bolsillos, llaves min, liga de 3cm.
G11: 1 | H11: Azul M. | I11: XL | J11: 100 | M11: =J11*G11 -> 100 | R11: 10 | S11: Chalecos acolchados | T11: Varón | U11: Mojado coreano, polar andino, cierre nylon, cierres nylon para 3 bolsillos, llaves min, cinta de ribete elástica de 2cm del color de la prenda.
C12: 13 | E12: 1 | F12: Bomber Varón | G12: 1 | H12: Negro | I12: L | J12: 100 | K12: Potosí | L12: Rossell | M12: =J12*G12 -> 100 | R12: 11 | S12: Joggers | T12: Unisex | U12: Terry, wato del color de la prenda, liga de 4cm.
C13: 15 | E13: 1 | F13: Bomber Varón | G13: 1 | H13: Negro | I13: XL | J13: =280/3 -> 93.333333 | K13: Ceibo | L13: Rossell | M13: =J13*G13 -> 93.333333 | R13: 12 | S13: Canguros | T13: Varón | U13: Terry.
G14: 1 | H14: Verde M. | I14: XL | J14: =280/3 -> 93.333333 | M14: =J14*G14 -> 93.333333
G15: 1 | H15: Guindo | I15: XL | J15: =280/3 -> 93.333333 | M15: =J15*G15 -> 93.333333 | R15: 13 | S15: Canguros | T15: Dama | U15: Terry.
C16: 17 | E16: 1 | F16: Bomber Varón | G16: 1 | H16: Negro | I16: L | J16: 80 | K16: Puente Avaroa | L16: David | M16: =J16*G16 -> 80 | R16: 14 | S16: Polerones | T16: Varón | U16: Terry, pretina de polera.
C17: 18 | E17: 1 | F17: Bomber Varón | G17: 1 | H17: Negro | I17: L | J17: 100 | K17: Potosí | L17: Rossell | M17: =J17*G17 -> 100 | R17: 15 | S17: Chamarras acolchadas | T17: Varón | U17: Taslan arrugado, fibra, polar plusher, terry, pretina común del color de la prenda, cierrre coreano normal del color de la prenda, llave especial
C18: 19 | E18: 1 | F18: Bomber Varón | G18: 1 | H18: Azul M. | I18: XL | J18: 105 | K18: Cementerio General | L18: Rossell | M18: =J18*G18 -> 105 | R18: 16 | S18: Chamarras acolchadas | T18: Dama | U18: Taslan arrugado, fibra, polar plusher, terry, pretina común del color de la prenda, cierrre coreano normal del color de la prenda, llave especial
C19: 21 | E19: 1 | F19: Bomber Varón | G19: 1 | H19: Negro | I19: XL | J19: 110 | K19: Garita | L19: Rossell | M19: =J19*G19 -> 110 | R19: 17 | S19: =S18 -> Chamarras acolchadas | T19: =T18 -> Dama | U19: =U18 -> Taslan arrugado, fibra, polar plusher, terry, pretina común del color de la prenda, cierrre coreano normal del color de la prenda, llave especial
C20: 22 | E20: 1 | F20: Bomber Varón | G20: 1 | H20: Azul M. | I20: L | J20: 110 | K20: Correos | L20: Rossell | M20: =J20*G20 -> 110 | R20: 18 | S20: Bomber polinylon | T20: Varón | U20: Polinylon, polar andino, tafeta, tira de 150 cm de pretina poliéster, cierre nylon oro, llaves especiales
C21: 23 | E21: 1 | F21: Bomber Varón | G21: 2 | H21: Negro | I21: L | J21: 90 | K21: Correos | L21: Rossell | M21: =J21*G21 -> 180 | R21: 19 | S21: Bomber polinylon | T21: Dama | U21: Polinylon, polar andino, tafeta, tira de 150 cm de pretina poliéster, cierre nylon oro, llaves especiales
C22: 24 | E22: 1 | F22: Bomber Varón | G22: 1 | H22: Verde M. | I22: M | J22: 100 | K22: Los Pinos | L22: Rossell | M22: =J22*G22 -> 100 | R22: 20 | S22: Chaqueta Camisa | T22: Varón | U22: Kaki 1ra, Tafeta, Cierre Nylon ORO, Tira pretina grueso, pellón.
C23: 27 | D23: 45661 | E23: 1 | F23: Bomber Varón | G23: 1 | H23: Negro | I23: L | J23: 100 | K23: Estación central | L23: Rossell | M23: =J23*G23 -> 100 | R23: 21 | S23: Nuevo Bomber Entero | T23: Varón | U23: Jaypura, polar andino, tafeta, pretina poliéster primera, cierre nylon ORO, cierre xm nylon ORO con llave ORO.
C24: 28 | D24: 45661 | E24: 1 | F24: Bomber Varón | G24: 1 | H24: Azul M. | I24: XL | J24: 110 | K24: Estación central | L24: Rossell | M24: =J24*G24 -> 110 | R24: 22 | S24: Canguros | T24: Varón | U24: Terry y cierre nylon normal centreal.
C25: 29 | D25: 45661 | E25: 1 | F25: Bomber Varón | G25: 1 | H25: Guindo | I25: M | J25: 100 | K25: Tlf. 6 de marzo | L25: Rossell | M25: =J25*G25 -> 100
C26: 30 | D26: 45661 | E26: 1 | F26: Bomber Varón | G26: 1 | H26: Azul M. | I26: XL | J26: 100 | K26: Ceibo | L26: Rossell | M26: =J26*G26 -> 100
C27: 32 | D27: 45662 | E27: 1 | F27: Bomber Varón | G27: 1 | H27: Negro | I27: XL | J27: 100 | K27: 3 de mayo | L27: Rossell | M27: =J27*G27 -> 100
G28: 1 | H28: Verde M. | I28: XL | J28: 100 | M28: =J28*G28 -> 100
C29: 33 | D29: 45662 | E29: 1 | F29: Bomber Varón | G29: 1 | H29: Verde M. | I29: L | J29: 100 | K29: San Pedro | L29: Rossell | M29: =J29*G29 -> 100
C30: 37 | D30: 45663 | E30: 1 | F30: Bomber Varón | G30: 1 | H30: Negro | I30: L | J30: 100 | K30: Estación central | L30: Rossell | M30: =J30*G30 -> 100
C31: 37 | D31: 45663 | E31: 1 | F31: Bomber Varón | G31: 1 | H31: Negro | I31: L | J31: 100 | K31: Correos | L31: Rossell | M31: =J31*G31 -> 100
C32: 38 | D32: 45663 | E32: 1 | F32: Bomber Varón | G32: 1 | H32: Azul M. | I32: M | J32: 100 | K32: Potosí | L32: Rossell | M32: =J32*G32 -> 100
C33: 41 | D33: 45664 | E33: 1 | F33: Bomber Varón | G33: 1 | H33: Negro | I33: XL | J33: 100 | K33: Tlf. 16 de julio | L33: Rossell | M33: =J33*G33 -> 100
G34: 1 | H34: Azul M. | I34: XL | J34: 100 | M34: =J34*G34 -> 100
C35: 42 | D35: 45664 | E35: 1 | F35: Bomber Varón | G35: 1 | H35: Negro | I35: L | J35: 100 | K35: Landaeta | L35: Rossell | M35: =J35*G35 -> 100
C36: 43 | D36: 45664 | E36: 1 | F36: Bomber Varón | G36: 1 | H36: Guindo | I36: XL | J36: 100 | K36: Col. Sánchez Bustamante | L36: Rossell | M36: =J36*G36 -> 100
G37: 1 | H37: Verde M. | I37: XL | J37: 100 | M37: =J37*G37 -> 100
C38: 48 | D38: 45664 | E38: 1 | F38: Bomber Varón | G38: 1 | H38: Negro | I38: L | J38: 100 | K38: San Francisco | L38: Rossell | M38: =J38*G38 -> 100
C39: 49 | D39: 45664 | E39: 1 | F39: Bomber Varón | G39: 1 | H39: Negro | I39: L | J39: 100 | K39: San Francisco | L39: Rossell | M39: =J39*G39 -> 100
C40: 52 | D40: 45665 | E40: 1 | F40: Bomber Varón | G40: 1 | H40: Negro | I40: XL | J40: 110 | K40: Sucre | L40: Rossell | M40: =J40*G40 -> 110
C41: 55 | D41: 45665 | E41: 1 | F41: Bomber Varón | G41: 1 | H41: Negro | I41: M | J41: 100 | K41: Potosí | L41: Rossell | M41: =J41*G41 -> 100
C42: 56 | D42: 45665 | E42: 1 | F42: Bomber Varón | G42: 1 | H42: Guindo | I42: XL | J42: 100 | K42: San Francisco | L42: Rossell | M42: =J42*G42 -> 100
G43: 1 | H43: Negro | I43: XL | J43: 100 | M43: =J43*G43 -> 100
C44: 58 | D44: 45661 | E44: 1 | F44: Bomber Varón | G44: 1 | H44: Guindo | I44: L | J44: 80 | K44: Ceibo | L44: David | M44: =J44*G44 -> 80
C45: 59 | D45: 45661 | E45: 1 | F45: Bomber Varón | G45: 1 | H45: Azul M. | I45: L | J45: 80 | K45: Puente Avaroa | L45: David | M45: =J45*G45 -> 80
C46: 60 | D46: 45661 | E46: 1 | F46: Bomber Varón | G46: 1 | H46: Azul M. | I46: L | J46: 80 | K46: Correos | L46: David | M46: =J46*G46 -> 80
C47: 61 | D47: 45666 | E47: 1 | F47: Bomber Varón | G47: 1 | H47: Azul M. | I47: XL | J47: 110 | K47: Tlf. 16 de julio | L47: Rossell | M47: =J47*G47 -> 110
C48: 62 | D48: 45666 | E48: 1 | F48: Bomber Varón | G48: 1 | H48: Verde M. | I48: XL | J48: 101 | K48: Oruro | L48: Rossell | M48: =J48*G48 -> 101
G49: 1 | H49: Negro | I49: XL | J49: 101 | M49: =J49*G49 -> 101
C50: 63 | D50: 45666 | E50: 1 | F50: Bomber Varón | G50: 1 | H50: Guindo | I50: XL | J50: 100 | K50: Feria de autos | L50: Rossell | M50: =J50*G50 -> 100
G51: 1 | H51: Verde M. | I51: XL | J51: 100 | M51: =J51*G51 -> 100
M52: =J52*G52 -> 0
M53: =J53*G53 -> 0
M54: =J54*G54 -> 0
M55: =J55*G55 -> 0
M56: =J56*G56 -> 0
M57: =J57*G57 -> 0
M58: =J58*G58 -> 0
M59: =J59*G59 -> 0
M60: =J60*G60 -> 0
M61: =J61*G61 -> 0
M62: =J62*G62 -> 0
M63: =J63*G63 -> 0
... M1125: =J1125*G1125 -> 0

Sheet Diseño de prenda
C1: CREACIÓN DE DISEÑO DE PRENDA
C3: Código | D3: Tipo de prenda | F3: Género | G3: Temporada | I3: Dpto. objetivo | M3: Medidas
M4: Concepto | N4: cm
C5: Descripción | F5: Materiales | M5: Alto de prenda
M6: Ancho de prenda
M7: Línea de sisa
M8: Línea de cintura
M9: Línea de basta
M10: Caída de hombro
M11: Hombro a hombro
D12: Escala de tallas | M12: Ancho de cuello del.
D13: Concepto | E13: S | F13: M | G13: L | H13: XL | I13: XXL | J13: XXL | M13: Ancho de cuello esp.
D14: =M5 -> Alto de prenda | M14: Alto de cuello
D15: =M6 -> Ancho de prenda | M15: Largo de manga
D16: =M7 -> Línea de sisa | M16: Alto de copa
D17: =M8 -> Línea de cintura | M17: Ancho de puño
D18: =M9 -> Línea de basta | M18: Medida de pretina
D19: =M10 -> Caída de hombro
D20: =M11 -> Hombro a hombro
D21: =M12 -> Ancho de cuello del.
D22: =M14 -> Alto de cuello
D23: =M15 -> Largo de manga
D24: =M16 -> Alto de copa
D25: =M17 -> Ancho de puño | M25: Fecha
D26: =M18 -> Medida de pretina
